{
  "Version": "2012-10-17",
  "Statement": [
    {
      "Sid": "ECSReadAccess",
      "Effect": "Allow",
      "Action": [
        "ecs:DescribeServices",
        "ecs:DescribeTasks",
        "ecs:DescribeTaskDefinition",
        "ecs:DescribeClusters",
        "ecs:ListTasks",
        "ecs:ListClusters",
        "ecs:ListServices"
      ],
      "Resource": "*"
    },
    {
      "Sid": "CloudWatchLogsReadAccess",
      "Effect": "Allow",
      "Action": [
        "logs:GetLogEvents",
        "logs:FilterLogEvents",
        "logs:DescribeLogStreams"
      ],
      "Resource": "arn:aws:logs:*:*:log-group:/ecs/*:*"
    },
    {
      "Sid": "CloudWatchMetricsReadAccess",
      "Effect": "Allow",
      "Action": [
        "cloudwatch:GetMetricData",
        "cloudwatch:GetMetricStatistics"
      ],
      "Resource": "*"
    },
    {
      "Sid": "ALBReadAccess",
      "Effect": "Allow",
      "Action": ["elasticloadbalancing:DescribeTargetHealth"],
      "Resource": "*"
    },
    {
      "Sid": "EC2NetworkReadAccess",
      "Effect": "Allow",
      "Action": [
        "ec2:DescribeSecurityGroups",
        "ec2:DescribeSubnets",
        "ec2:DescribeRouteTables",
        "ec2:DescribeNatGateways",
        "ec2:DescribeNetworkInterfaces"
      ],
      "Resource": "*"
    },
    {
      "Sid": "STSIdentity",
      "Effect": "Allow",
      "Action": ["sts:GetCallerIdentity"],
      "Resource": "*"
    }
  ]
}
